MANIFEST.in
account_budget_demo.xml
account_budget_report.xml
account_budget_view.xml
account_budget_workflow.xml
setup.py
./__init__.py
./__openerp__.py
./account_budget.py
./report/__init__.py
./report/analytic_account_budget_report.py
./report/budget_report.py
./report/crossovered_budget_report.py
./wizard/__init__.py
./wizard/account_budget_analytic.py
./wizard/account_budget_crossovered_report.py
./wizard/account_budget_crossovered_summary_report.py
./wizard/account_budget_report.py
i18n/account_budget.pot
i18n/ar.po
i18n/bg.po
i18n/bs.po
i18n/ca.po
i18n/cs.po
i18n/da.po
i18n/de.po
i18n/el.po
i18n/en_GB.po
i18n/es.po
i18n/es_AR.po
i18n/es_CR.po
i18n/es_EC.po
i18n/es_MX.po
i18n/es_PY.po
i18n/es_VE.po
i18n/et.po
i18n/fa.po
i18n/fi.po
i18n/fr.po
i18n/gl.po
i18n/gu.po
i18n/he.po
i18n/hi.po
i18n/hr.po
i18n/hu.po
i18n/id.po
i18n/it.po
i18n/ja.po
i18n/ko.po
i18n/lo.po
i18n/lt.po
i18n/lv.po
i18n/mk.po
i18n/mn.po
i18n/nb.po
i18n/nl.po
i18n/nl_BE.po
i18n/oc.po
i18n/pl.po
i18n/pt.po
i18n/pt_BR.po
i18n/ro.po
i18n/ru.po
i18n/sl.po
i18n/sq.po
i18n/sr.po
i18n/sr@latin.po
i18n/sv.po
i18n/tlh.po
i18n/tr.po
i18n/uk.po
i18n/vi.po
i18n/zh_CN.po
i18n/zh_TW.po
images/budget.jpeg
images/budgetary_position.jpeg
openerp_account_budget.egg-info/PKG-INFO
openerp_account_budget.egg-info/SOURCES.txt
openerp_account_budget.egg-info/dependency_links.txt
openerp_account_budget.egg-info/requires.txt
openerp_account_budget.egg-info/top_level.txt
report/analytic_account_budget_report.rml
report/analytic_account_budget_report.sxw
report/budget_report.rml
report/budget_report.sxw
report/crossovered_budget_report.rml
report/crossovered_budget_report.sxw
security/account_budget_security.xml
security/ir.model.access.csv
test/account_budget.yml
test/account_budget_report.yml
test/account_budget_spread.yml
wizard/account_budget_analytic_view.xml
wizard/account_budget_crossovered_report_view.xml
wizard/account_budget_crossovered_summary_report_view.xml
wizard/account_budget_report_view.xml